{
    "lang":  "Nederlands",
    "trans":  [
                  {
                      "key":  "Chinese",
                      "value":  "Chinese"
                  },
                  {
                      "key":  "traditional Chinese",
                      "value":  "traditioneel Chinees"
                  },
                  {
                      "key":  "Cantonese",
                      "value":  "KantoneesName"
                  },
                  {
                      "key":  "classical Chinese",
                      "value":  "klassiek Chinees"
                  },
                  {
                      "key":  "Japanese",
                      "value":  "Japans"
                  },
                  {
                      "key":  "Korean",
                      "value":  "Koreaans"
                  },
                  {
                      "key":  "French",
                      "value":  "Frans"
                  },
                  {
                      "key":  "Spanish",
                      "value":  "Spaans"
                  },
                  {
                      "key":  "Thai",
                      "value":  "Thai."
                  },
                  {
                      "key":  "Arabic",
                      "value":  "Arabisch"
                  },
                  {
                      "key":  "Russian",
                      "value":  "Russisch"
                  },
                  {
                      "key":  "Portuguese",
                      "value":  "Portugees"
                  },
                  {
                      "key":  "German",
                      "value":  "Duits"
                  },
                  {
                      "key":  "Italian",
                      "value":  "Italiaans"
                  },
                  {
                      "key":  "Greek",
                      "value":  "Grieks"
                  },
                  {
                      "key":  "Dutch",
                      "value":  "Nederlands"
                  },
                  {
                      "key":  "Polish",
                      "value":  "Pools"
                  },
                  {
                      "key":  "Bulgarian",
                      "value":  "Bulgaars"
                  },
                  {
                      "key":  "Estonian",
                      "value":  "Ests"
                  },
                  {
                      "key":  "Danish",
                      "value":  "Deens"
                  },
                  {
                      "key":  "Finnish",
                      "value":  "Fins"
                  },
                  {
                      "key":  "Czech",
                      "value":  "Tsjechisch"
                  },
                  {
                      "key":  "Romanian",
                      "value":  "Roemeens"
                  },
                  {
                      "key":  "Slovenian",
                      "value":  "Sloveens"
                  },
                  {
                      "key":  "Swedish",
                      "value":  "Zweeds"
                  },
                  {
                      "key":  "Hungarian",
                      "value":  "Hongaars"
                  },
                  {
                      "key":  "Vietnamese",
                      "value":  "Vietnamees"
                  },
                  {
                      "key":  "Corner",
                      "value":  "Hoek"
                  },
                  {
                      "key":  "Elemkeytary streams",
                      "value":  "Elemkeytaire stromen"
                  },
                  {
                      "key":  "Fireworks dancing",
                      "value":  "Vuurwerk dansen"
                  },
                  {
                      "key":  "Round",
                      "value":  "Rondom"
                  },
                  {
                      "key":  "Gradiant",
                      "value":  "Gradiant."
                  },
                  {
                      "key":  "Badget",
                      "value":  "Badget."
                  },
                  {
                      "key":  "Barrage",
                      "value":  "Barrage"
                  },
                  {
                      "key":  "Label",
                      "value":  "Label"
                  },
                  {
                      "key":  "ProgressBar",
                      "value":  "Progressiebalk"
                  },
                  {
                      "key":  "Scrolling",
                      "value":  "Scrollen"
                  },
                  {
                      "key":  "Mkeyu",
                      "value":  "MkeyuGenericName"
                  },
                  {
                      "key":  "TaoQuick",
                      "value":  "TaoQuick."
                  },
                  {
                      "key":  "Blue",
                      "value":  "Blauw"
                  },
                  {
                      "key":  "Frostmourne",
                      "value":  "Frostmourn"
                  },
                  {
                      "key":  "Welcome to the \u0027TaoQuick\u0027 demo program",
                      "value":  "Welkom bij het\u0027TaoQuick\u0027demo programma"
                  },
                  {
                      "key":  "Welcome",
                      "value":  "Welkom."
                  },
                  {
                      "key":  "Close",
                      "value":  "Sluiten"
                  },
                  {
                      "key":  "Green",
                      "value":  "Groen"
                  },
                  {
                      "key":  "QRcode",
                      "value":  "QRcode"
                  },
                  {
                      "key":  "Shadow flow",
                      "value":  "Stroom van schaduw"
                  },
                  {
                      "key":  "Drop-down",
                      "value":  "Afval"
                  },
                  {
                      "key":  "Graphic",
                      "value":  "Grafisch"
                  },
                  {
                      "key":  "Basic",
                      "value":  "Basis"
                  },
                  {
                      "key":  "Joy of fire",
                      "value":  "Vreugde van het vuur"
                  },
                  {
                      "key":  "Cool",
                      "value":  "Cool."
                  },
                  {
                      "key":  "Pink",
                      "value":  "Roze"
                  },
                  {
                      "key":  "IP address",
                      "value":  "IP-adres"
                  },
                  {
                      "key":  "Home",
                      "value":  "Thuis"
                  },
                  {
                      "key":  "Drag",
                      "value":  "Drag"
                  },
                  {
                      "key":  "Text",
                      "value":  "Tekst"
                  },
                  {
                      "key":  "keyergy ball",
                      "value":  "keyer bal"
                  },
                  {
                      "key":  "Red",
                      "value":  "Rood"
                  },
                  {
                      "key":  "Button",
                      "value":  "Knop"
                  },
                  {
                      "key":  "Gold",
                      "value":  "Goud"
                  },
                  {
                      "key":  "Black",
                      "value":  "Zwart"
                  },
                  {
                      "key":  "Functional",
                      "value":  "Functioneel"
                  },
                  {
                      "key":  "Comet Halley",
                      "value":  "Comet Halley."
                  },
                  {
                      "key":  "Gradient",
                      "value":  "Gradiënt"
                  },
                  {
                      "key":  "Background",
                      "value":  "Achtergrond"
                  },
                  {
                      "key":  "Dialog",
                      "value":  "Dialoog"
                  },
                  {
                      "key":  "ShaderEffect",
                      "value":  "Schaduweffect"
                  },
                  {
                      "key":  "Cloud Hole",
                      "value":  "Cloud Hole."
                  },
                  {
                      "key":  "Star Light",
                      "value":  "Star Light."
                  },
                  {
                      "key":  "Snail",
                      "value":  "Slang"
                  },
                  {
                      "key":  "Super Mario",
                      "value":  "Super Mario."
                  },
                  {
                      "key":  "Effect",
                      "value":  "Effect"
                  },
                  {
                      "key":  "Ring",
                      "value":  "Ring"
                  },
                  {
                      "key":  "Brilliant Starry Sky",
                      "value":  "Briljant Starry Sky."
                  },
                  {
                      "key":  "Keep up with the pace",
                      "value":  "Blijf bij met het tempo"
                  },
                  {
                      "key":  "Undercurrent surge",
                      "value":  "Onderlopende golf"
                  },
                  {
                      "key":  "Magic Circle",
                      "value":  "Magische cirkel"
                  },
                  {
                      "key":  "Painter",
                      "value":  "Schilder"
                  },
                  {
                      "key":  "RoundRect",
                      "value":  "RoundRect"
                  },
                  {
                      "key":  "KLine",
                      "value":  "KLine."
                  },
                  {
                      "key":  "Animation",
                      "value":  "Animatie"
                  },
                  {
                      "key":  "Enter",
                      "value":  "Voer"
                  },
                  {
                      "key":  "Grad",
                      "value":  "Grad"
                  },
                  {
                      "key":  "Cleavage",
                      "value":  "Scheuring"
                  },
                  {
                      "key":  "Diagonal",
                      "value":  "Diagonaal"
                  },
                  {
                      "key":  "Louver",
                      "value":  "Louver"
                  },
                  {
                      "key":  "Square",
                      "value":  "Vierkant"
                  },
                  {
                      "key":  "Circle",
                      "value":  "Cirkel"
                  },
                  {
                      "key":  "Cross",
                      "value":  "Kruis"
                  },
                  {
                      "key":  "Rhombus",
                      "value":  "Rhombus.kgm"
                  },
                  {
                      "key":  "Wheel",
                      "value":  "Wiel"
                  },
                  {
                      "key":  "Board",
                      "value":  "Raad"
                  },
                  {
                      "key":  "Dissolve",
                      "value":  "Ontploffen"
                  },
                  {
                      "key":  "PageSwitch",
                      "value":  "Paginaswitch"
                  },
                  {
                      "key":  "FadeInOut",
                      "value":  "FadeInOutComment"
                  }
              ]
}
